great_expectations_cloud/__init__.py
great_expectations_cloud/agent/__init__.py
great_expectations_cloud/agent/actions/__init__.py
great_expectations_cloud/agent/actions/agent_action.py
great_expectations_cloud/agent/actions/draft_datasource_config_action.py
great_expectations_cloud/agent/actions/generate_data_quality_check_expectations_action.py
great_expectations_cloud/agent/actions/list_asset_names.py
great_expectations_cloud/agent/actions/run_checkpoint.py
great_expectations_cloud/agent/actions/run_metric_list_action.py
great_expectations_cloud/agent/actions/run_scheduled_checkpoint.py
great_expectations_cloud/agent/actions/run_window_checkpoint.py
great_expectations_cloud/agent/actions/unknown.py
great_expectations_cloud/agent/actions/utils.py
great_expectations_cloud/agent/agent.py
great_expectations_cloud/agent/agent_warnings.py
great_expectations_cloud/agent/cli.py
great_expectations_cloud/agent/config.py
great_expectations_cloud/agent/constants.py
great_expectations_cloud/agent/event_handler.py
great_expectations_cloud/agent/exceptions.py
great_expectations_cloud/agent/message_service/__init__.py
great_expectations_cloud/agent/message_service/asyncio_rabbit_mq_client.py
great_expectations_cloud/agent/message_service/subscriber.py
great_expectations_cloud/agent/models.py
great_expectations_cloud/agent/run.py
great_expectations_cloud/agent/utils.py
great_expectations_cloud/logging/README.md
great_expectations_cloud/logging/logging_cfg.py
great_expectations_cloud/py.typed
great_expectations_cloud-20260130.0.dist-info/METADATA
great_expectations_cloud-20260130.0.dist-info/WHEEL
great_expectations_cloud-20260130.0.dist-info/entry_points.txt
great_expectations_cloud-20260130.0.dist-info/licenses/LICENSE
great_expectations_cloud-20260130.0.dist-info/RECORD
