Metadata-Version: 2.4
Name: great_expectations_cloud
Version: 20260130.0
Summary: Great Expectations Cloud
License: Proprietary
License-File: LICENSE
Author: The Great Expectations Team
Author-email: team@greatexpectations.io
Requires-Python: >=3.11.4,<3.12
Classifier: Development Status :: 3 - Alpha
Classifier: Intended Audience :: Developers
Classifier: Intended Audience :: Science/Research
Classifier: License :: Other/Proprietary License
Classifier: Programming Language :: Python :: 3
Classifier: Topic :: Scientific/Engineering
Classifier: Topic :: Scientific/Engineering :: Information Analysis
Classifier: Topic :: Software Development :: Quality Assurance
Classifier: Topic :: Software Development :: Testing
Requires-Dist: great-expectations[databricks,gx-redshift,mssql,postgresql,snowflake,trino] (==1.11.3)
Requires-Dist: orjson (>=3.9.7,<4.0.0,!=3.9.10)
Requires-Dist: packaging (>=21.3,<27.0)
Requires-Dist: pika (>=1.3.1,<2.0.0)
Requires-Dist: pydantic (>=2.8.1,<3)
Requires-Dist: setuptools (==80.10.2)
Requires-Dist: sqlalchemy (>=2.0)
Requires-Dist: tenacity (>=8.2.3,<10.0.0)
Project-URL: Homepage, https://greatexpectations.io
Project-URL: Repository, https://github.com/great-expectations/cloud
